{
	"name": "dplsim",
    "version": "~master",
    "targetPath": "bin",
    "targetType": "executable",
    "importPaths": [ "DerelictCL/source", "descl/import", "derelict/import", "descore/import", "des/import" ],
    "sourcePaths": [ "DerelictCL/source", "descl/import", "derelict/import", "descore/import", "des/import", "src" ],
    "libs-posix": [ "dl" ],
    "lflags": [ "-L./derelict/lib/dmd" ],
    "dflags-dmd": [ "-Jsrc" ],
    "libs":
    [
        "DerelictUtil",
        "DerelictFT",
        "DerelictGL3",
        "DerelictIL",
        "DerelictSDL2"
    ]
}
